CHANGES
LICENSE
MANIFEST.in
README.rst
setup.py
django_watermark_zemi4.egg-info/PKG-INFO
django_watermark_zemi4.egg-info/SOURCES.txt
django_watermark_zemi4.egg-info/dependency_links.txt
django_watermark_zemi4.egg-info/not-zip-safe
django_watermark_zemi4.egg-info/requires.txt
django_watermark_zemi4.egg-info/top_level.txt
watermarker/__init__.py
watermarker/admin.py
watermarker/conf.py
watermarker/models.py
watermarker/utils.py
watermarker/locale/ru/LC_MESSAGES/django.mo
watermarker/locale/ru/LC_MESSAGES/django.po
watermarker/migrations/0001_initial.py
watermarker/migrations/__init__.py
watermarker/south_migrations/0001_initial.py
watermarker/south_migrations/__init__.py
watermarker/templatetags/__init__.py
watermarker/templatetags/watermark.py